nwdiag/__init__.py
nwdiag/builder.py
nwdiag/command.py
nwdiag/drawer.py
nwdiag/elements.py
nwdiag/metrics.py
nwdiag/parser.py
nwdiag/tests/__init__.py
nwdiag/tests/test_builder.py
nwdiag/tests/test_generate_diagram.py
nwdiag/tests/test_rst_directives.py
nwdiag/tests/utils.py
nwdiag/tests/VLGothic/LICENSE
nwdiag/tests/VLGothic/LICENSE.en
nwdiag/tests/VLGothic/LICENSE_E.mplus
nwdiag/tests/VLGothic/LICENSE_J.mplus
nwdiag/tests/VLGothic/VL-Gothic-Regular.ttf
nwdiag/tests/diagrams/autoexpand_node_width.diag
nwdiag/tests/diagrams/connected_networks.diag
nwdiag/tests/diagrams/connected_networks2.diag
nwdiag/tests/diagrams/connected_networks3.diag
nwdiag/tests/diagrams/diagram_attributes.diag
nwdiag/tests/diagrams/group_across_network.diag
nwdiag/tests/diagrams/group_and_peer_network.diag
nwdiag/tests/diagrams/group_inner_network.diag
nwdiag/tests/diagrams/group_network.diag
nwdiag/tests/diagrams/group_outer_network.diag
nwdiag/tests/diagrams/node_address_attribute.diag
nwdiag/tests/diagrams/node_attributes.diag
nwdiag/tests/diagrams/node_belongs_to_multiple_networks.diag
nwdiag/tests/diagrams/node_including_hyphen.diag
nwdiag/tests/diagrams/peer_network.diag
nwdiag/tests/diagrams/peer_network2.diag
nwdiag/tests/diagrams/peer_network3.diag
nwdiag/tests/diagrams/peer_network4.diag
nwdiag/tests/diagrams/peer_network5.diag
nwdiag/tests/diagrams/peer_network_branched.diag
nwdiag/tests/diagrams/same_peer_network.diag
nwdiag/tests/diagrams/single_network.diag
nwdiag/tests/diagrams/split_group.diag
nwdiag/tests/diagrams/two_networks.diag
nwdiag/tests/diagrams/errors/peer_network_in_same_node.diag
nwdiag/utils/__init__.py
nwdiag/utils/rst/__init__.py
nwdiag/utils/rst/directives.py
nwdiag/utils/rst/nodes.py
packetdiag/__init__.py
packetdiag/builder.py
packetdiag/command.py
packetdiag/drawer.py
packetdiag/elements.py
packetdiag/metrics.py
packetdiag/noderenderers.py
packetdiag/parser.py
packetdiag/tests/test_generate_diagram.py
packetdiag/tests/test_rst_directives.py
nwdiag-3.0.0.dist-info/LICENSE
nwdiag-3.0.0.dist-info/METADATA
nwdiag-3.0.0.dist-info/WHEEL
nwdiag-3.0.0.dist-info/entry_points.txt
nwdiag-3.0.0.dist-info/top_level.txt
nwdiag-3.0.0.dist-info/RECORD
